Workbook

Sheet Settings
A1: Pricing settings (change the yellow cells; every price updates)
A2: USD to ZAR exchange rate | B2: 16.46 | C2: Source: currencyconvert.online, 14 Oct 2026 05:00 UTC (R16.4573)
A3: Shipping, clearing & duty (machines) | B3: 0.15 | C3: Estimate: % of factory price to land a machine in Durban. Replace with your real figure.
A4: Shipping, clearing & duty (consumables) | B4: 0.3 | C4: Estimate: small items cost more per rand to ship.
A5: Markup on landed cost | B5: 0.375 | C5: You asked for 35-40%; 37.5% is the middle. Change per row in the Prices sheet if needed.
A6: Round website price up to nearest (R) | B6: 50
A8: How the price is worked out
A9: 1. Estimated factory price (USD): from Made-in-China.com listings for the same type of machine, scaled to Alibaba factory level so it lines up with your 21 existing prices.
A10: 2. Landed cost (R) = factory price x exchange rate x (1 + shipping, clearing & duty).
A11: 3. Website price = landed cost x (1 + markup), rounded up to the nearest R50.
A12: Blue numbers are estimates you can overwrite with your real supplier price (USD). Confidence shows how sure the estimate is: replace Low ones first.
A13: Alibaba blocks automated reading, so these are not your actual supplier quotes. Check before relying on them.

Sheet Prices
A1: # | B1: Machine | C1: Model | D1: Category | E1: Est. factory price (USD) | F1: Confidence | G1: Basis for the estimate | H1: Shipping, clearing & duty % | I1: Landed cost (R) | J1: Markup % | K1: Website price (R) | L1: Profit per sale (R) | M1: Margin on price % | N1: Link
A2: 53 | B2: 6-Handle Vacuum Roller Body & Face Machine | C2: TAVR6 | D2: Body massage | E2: 1600 | F2: Medium | G2: Made-in-China vacuum roller listings US$1,100-4,200; your 360 roller R18,599 as anchor | H2: =IF(D2="Consumables",Settings!$B$4,Settings!$B$3) -> 0.15 | I2: =E2*Settings!$B$2*(1+H2) -> 30286.4 | J2: =Settings!$B$5 -> 0.375 | K2: =CEILING(I2*(1+J2),Settings!$B$6) -> 41650 | L2: =K2-I2 -> 11363.6 | M2: =IF(K2=0,0,L2/K2) -> 0.27283553 | N2: https://trimionafrica.co.za/p/m53
A3: 54 | B3: 5-Handle Vacuum Roller Body Machine | C3: TAVR5 | D3: Body massage | E3: 1450 | F3: Medium | G3: Made-in-China vacuum roller listings US$1,100-4,200; your 360 roller R18,599 as anchor | H3: =IF(D3="Consumables",Settings!$B$4,Settings!$B$3) -> 0.15 | I3: =E3*Settings!$B$2*(1+H3) -> 27447.05 | J3: =Settings!$B$5 -> 0.375 | K3: =CEILING(I3*(1+J3),Settings!$B$6) -> 37750 | L3: =K3-I3 -> 10302.95 | M3: =IF(K3=0,0,L3/K3) -> 0.27292583 | N3: https://trimionafrica.co.za/p/m54
A4: 55 | B4: 2-Handle Vacuum Roller Machine | C4: TAVR2 | D4: Body massage | E4: 1000 | F4: Medium | G4: Made-in-China vacuum roller listings US$1,100-4,200; your 360 roller R18,599 as anchor | H4: =IF(D4="Consumables",Settings!$B$4,Settings!$B$3) -> 0.15 | I4: =E4*Settings!$B$2*(1+H4) -> 18929 | J4: =Settings!$B$5 -> 0.375 | K4: =CEILING(I4*(1+J4),Settings!$B$6) -> 26050 | L4: =K4-I4 -> 7121 | M4: =IF(K4=0,0,L4/K4) -> 0.27335893 | N4: https://trimionafrica.co.za/p/m55
A5: 56 | B5: 2-in-1 Pressotherapy System | C5: TAPT2 | D5: Body massage | E5: 380 | F5: Medium | G5: Made-in-China pressotherapy listings: 24 airbags US$699-999, EMS + far infrared US$439-599, suits US$800-1,300 | H5: =IF(D5="Consumables",Settings!$B$4,Settings!$B$3) -> 0.15 | I5: =E5*Settings!$B$2*(1+H5) -> 7193.02 | J5: =Settings!$B$5 -> 0.375 | K5: =CEILING(I5*(1+J5),Settings!$B$6) -> 9900 | L5: =K5-I5 -> 2706.98 | M5: =IF(K5=0,0,L5/K5) -> 0.27343232 | N5: https://trimionafrica.co.za/p/m56
A6: 57 | B6: 3-in-1 Pressotherapy System | C6: TAPT3 | D6: Body massage | E6: 480 | F6: Medium | G6: Made-in-China pressotherapy listings: 24 airbags US$699-999, EMS + far infrared US$439-599, suits US$800-1,300 | H6: =IF(D6="Consumables",Settings!$B$4,Settings!$B$3) -> 0.15 | I6: =E6*Settings!$B$2*(1+H6) -> 9085.92 | J6: =Settings!$B$5 -> 0.375 | K6: =CEILING(I6*(1+J6),Settings!$B$6) -> 12500 | L6: =K6-I6 -> 3414.08 | M6: =IF(K6=0,0,L6/K6) -> 0.2731264 | N6: https://trimionafrica.co.za/p/m57
A7: 134 | B7: Far Infrared Pressotherapy System (16 Air Bags) | C7: TAPTF1 | D7: Body massage | E7: 380 | F7: Medium | G7: Made-in-China pressotherapy listings: 24 airbags US$699-999, EMS + far infrared US$439-599, suits US$800-1,300 | H7: =IF(D7="Consumables",Settings!$B$4,Settings!$B$3) -> 0.15 | I7: =E7*Settings!$B$2*(1+H7) -> 7193.02 | J7: =Settings!$B$5 -> 0.375 | K7: =CEILING(I7*(1+J7),Settings!$B$6) -> 9900 | L7: =K7-I7 -> 2706.98 | M7: =IF(K7=0,0,L7/K7) -> 0.27343232 | N7: https://trimionafrica.co.za/p/m134
A8: 135 | B8: Far Infrared Pressotherapy System II (16 Air Bags) | C8: TAPTF2 | D8: Body massage | E8: 380 | F8: Medium | G8: Made-in-China pressotherapy listings: 24 airbags US$699-999, EMS + far infrared US$439-599, suits US$800-1,300 | H8: =IF(D8="Consumables",Settings!$B$4,Settings!$B$3) -> 0.15 | I8: =E8*Settings!$B$2*(1+H8) -> 7193.02 | J8: =Settings!$B$5 -> 0.375 | K8: =CEILING(I8*(1+J8),Settings!$B$6) -> 9900 | L8: =K8-I8 -> 2706.98 | M8: =IF(K8=0,0,L8/K8) -> 0.27343232 | N8: https://trimionafrica.co.za/p/m135
A9: 136 | B9: 3-in-1 Far Infrared, EMS and Pressotherapy System | C9: TAPT3E | D9: Body massage | E9: 520 | F9: Medium | G9: Made-in-China pressotherapy listings: 24 airbags US$699-999, EMS + far infrared US$439-599, suits US$800-1,300 | H9: =IF(D9="Consumables",Settings!$B$4,Settings!$B$3) -> 0.15 | I9: =E9*Settings!$B$2*(1+H9) -> 9843.08 | J9: =Settings!$B$5 -> 0.375 | K9: =CEILING(I9*(1+J9),Settings!$B$6) -> 13550 | L9: =K9-I9 -> 3706.92 | M9: =IF(K9=0,0,L9/K9) -> 0.27357343 | N9: https://trimionafrica.co.za/p/m136
A10: 137 | B10: 3-in-1 Pressotherapy, EMS and Far Infrared Machine | C10: TAPT3P | D10: Body massage | E10: 450 | F10: Medium | G10: Made-in-China pressotherapy listings: 24 airbags US$699-999, EMS + far infrared US$439-599, suits US$800-1,300 | H10: =IF(D10="Consumables",Settings!$B$4,Settings!$B$3) -> 0.15 | I10: =E10*Settings!$B$2*(1+H10) -> 8518.05 | J10: =Settings!$B$5 -> 0.375 | K10: =CEILING(I10*(1+J10),Settings!$B$6) -> 11750 | L10: =K10-I10 -> 3231.95 | M10: =IF(K10=0,0,L10/K10) -> 0.27505957 | N10: https://trimionafrica.co.za/p/m137
A11: 138 | B11: 2-in-1 Far Infrared Pressotherapy Machine | C11: TAPT2F | D11: Body massage | E11: 330 | F11: Medium | G11: Made-in-China pressotherapy listings: 24 airbags US$699-999, EMS + far infrared US$439-599, suits US$800-1,300 | H11: =IF(D11="Consumables",Settings!$B$4,Settings!$B$3) -> 0.15 | I11: =E11*Settings!$B$2*(1+H11) -> 6246.57 | J11: =Settings!$B$5 -> 0.375 | K11: =CEILING(I11*(1+J11),Settings!$B$6) -> 8600 | L11: =K11-I11 -> 2353.43 | M11: =IF(K11=0,0,L11/K11) -> 0.27365465 | N11: https://trimionafrica.co.za/p/m138
A12: 139 | B12: 16-Air-Bag Pressotherapy Machine | C12: TAPT16 | D12: Body massage | E12: 350 | F12: Medium | G12: Made-in-China pressotherapy listings: 24 airbags US$699-999, EMS + far infrared US$439-599, suits US$800-1,300 | H12: =IF(D12="Consumables",Settings!$B$4,Settings!$B$3) -> 0.15 | I12: =E12*Settings!$B$2*(1+H12) -> 6625.15 | J12: =Settings!$B$5 -> 0.375 | K12: =CEILING(I12*(1+J12),Settings!$B$6) -> 9150 | L12: =K12-I12 -> 2524.85 | M12: =IF(K12=0,0,L12/K12) -> 0.27593989 | N12: https://trimionafrica.co.za/p/m139
A13: 140 | B13: 24-Air-Bag Pressotherapy Machine with Eye Massage | C13: TAPT24 | D13: Body massage | E13: 480 | F13: Medium | G13: Made-in-China pressotherapy listings: 24 airbags US$699-999, EMS + far infrared US$439-599, suits US$800-1,300 | H13: =IF(D13="Consumables",Settings!$B$4,Settings!$B$3) -> 0.15 | I13: =E13*Settings!$B$2*(1+H13) -> 9085.92 | J13: =Settings!$B$5 -> 0.375 | K13: =CEILING(I13*(1+J13),Settings!$B$6) -> 12500 | L13: =K13-I13 -> 3414.08 | M13: =IF(K13=0,0,L13/K13) -> 0.2731264 | N13: https://trimionafrica.co.za/p/m140
... A144: 159 | B144: Body Composition Analyser with Printer | C144: TABA1 | D144: Wellness and salon | E144: 800 | F144: Medium | G144: Made-in-China body composition analysers US$499-1,500 (with printer US$800-1,500) | H144: =IF(D144="Consumables",Settings!$B$4,Settings!$B$3) -> 0.15 | I144: =E144*Settings!$B$2*(1+H144) -> 15143.2 | J144: =Settings!$B$5 -> 0.375 | K144: =CEILING(I144*(1+J144),Settings!$B$6) -> 20850 | L144: =K144-I144 -> 5706.8 | M144: =IF(K144=0,0,L144/K144) -> 0.27370743 | N144: https://trimionafrica.co.za/p/m159
J146: Total if one of each sold | K146: =SUM(K2:K144) -> 3484250 | L146: =SUM(L2:L144) -> 952696.24

Sheet Already priced
A1: # | B1: Machine | C1: Model | D1: Category | E1: Price on site now (R) | F1: Implied factory price at same formula (USD)
A2: 1 | B2: 5-Handle 2500W EMS Body Sculpting Machine | C2: TAEMS2500 | D2: EMS and electromagnetic | E2: 143750 | F2: =E2/(Settings!$B$2*(1+Settings!$B$3)*(1+Settings!$B$5)) -> 5523.031
A3: 2 | B3: 4-Handle 4300W EMS Body Sculpting Machine | C3: TAEMS4300 | D3: EMS and electromagnetic | E3: 127650 | F3: =E3/(Settings!$B$2*(1+Settings!$B$3)*(1+Settings!$B$5)) -> 4904.4516
A4: 3 | B4: 4-Handle EMS Body Sculpting Machine | C4: TAEMS4 | D4: EMS and electromagnetic | E4: 43000 | F4: =E4/(Settings!$B$2*(1+Settings!$B$3)*(1+Settings!$B$5)) -> 1652.1067
A5: 4 | B5: 5000W 2-Handle EMS Body Sculpting Machine | C5: TAEMS5000 | D5: EMS and electromagnetic | E5: 22000 | F5: =E5/(Settings!$B$2*(1+Settings!$B$3)*(1+Settings!$B$5)) -> 845.26388
A6: 5 | B6: 2-Handle EMS Body Sculpting Machine | C6: TAEMS2 | D6: EMS and electromagnetic | E6: 20950 | F6: =E6/(Settings!$B$2*(1+Settings!$B$3)*(1+Settings!$B$5)) -> 804.92174
A7: 6 | B7: 10-Channel EMS Body System | C7: TAEMS10CH01 | D7: EMS and electromagnetic | E7: 7500 | F7: =E7/(Settings!$B$2*(1+Settings!$B$3)*(1+Settings!$B$5)) -> 288.15814
A8: 17 | B8: 4-Handle Vertical Electromagnetic Sculpting Station | C8: TAEM4V | D8: EMS and electromagnetic | E8: 44850 | F8: =E8/(Settings!$B$2*(1+Settings!$B$3)*(1+Settings!$B$5)) -> 1723.1857
A9: 31 | B9: 5-Handle Hot, Cold & EMS Machine | C9: TACRYO5 | D9: Cryo body contouring | E9: 60399 | F9: =E9/(Settings!$B$2*(1+Settings!$B$3)*(1+Settings!$B$5)) -> 2320.5951
A10: 32 | B10: Cryo Body Contouring Station | C10: TACRYO15 | D10: Cryo body contouring | E10: 17450 | F10: =E10/(Settings!$B$2*(1+Settings!$B$3)*(1+Settings!$B$5)) -> 670.44794
A11: 33 | B11: 3-Handle Cryo Body Contouring Machine | C11: TACRYO3 | D11: Cryo body contouring | E11: 17000 | F11: =E11/(Settings!$B$2*(1+Settings!$B$3)*(1+Settings!$B$5)) -> 653.15845
A12: 41 | B12: 448K RF Body Contouring Machine | C12: TARF448B | D12: RF and cavitation | E12: 13199 | F12: =E12/(Settings!$B$2*(1+Settings!$B$3)*(1+Settings!$B$5)) -> 507.11991
A13: 42 | B13: 448kHz Deep RF Body & Face Machine | C13: TARF448 | D13: RF and cavitation | E13: 101150 | F13: =E13/(Settings!$B$2*(1+Settings!$B$3)*(1+Settings!$B$5)) -> 3886.2928
... A22: 70 | B22: Professional Standing Hood Salon Hair Dryer | C22: TASHD01 | D22: Wellness and salon | E22: 6999 | F22: =E22/(Settings!$B$2*(1+Settings!$B$3)*(1+Settings!$B$5)) -> 268.90918
A24: These are your current prices, left unchanged. The last column shows they work out to factory-level costs, which is how the new estimates were calibrated.
